ansys/dpf/gate/__init__.py
ansys/dpf/gate/_version.py
ansys/dpf/gate/any_grpcapi.py
ansys/dpf/gate/collection_grpcapi.py
ansys/dpf/gate/common.py
ansys/dpf/gate/custom_type_field_grpcapi.py
ansys/dpf/gate/cyclic_support_grpcapi.py
ansys/dpf/gate/data_processing_grpcapi.py
ansys/dpf/gate/data_sources_grpcapi.py
ansys/dpf/gate/dpf_array.py
ansys/dpf/gate/dpf_data_tree_grpcapi.py
ansys/dpf/gate/dpf_vector.py
ansys/dpf/gate/errors.py
ansys/dpf/gate/field_definition_grpcapi.py
ansys/dpf/gate/field_grpcapi.py
ansys/dpf/gate/generic_data_container_grpcapi.py
ansys/dpf/gate/generic_support_grpcapi.py
ansys/dpf/gate/grpc_stream_helpers.py
ansys/dpf/gate/integral_types.py
ansys/dpf/gate/label_space_grpcapi.py
ansys/dpf/gate/load_api.py
ansys/dpf/gate/meshed_region_grpcapi.py
ansys/dpf/gate/misc.py
ansys/dpf/gate/object_handler.py
ansys/dpf/gate/operator_config_grpcapi.py
ansys/dpf/gate/operator_grpcapi.py
ansys/dpf/gate/operator_specification_grpcapi.py
ansys/dpf/gate/property_field_grpcapi.py
ansys/dpf/gate/result_info_grpcapi.py
ansys/dpf/gate/scoping_grpcapi.py
ansys/dpf/gate/session_grpcapi.py
ansys/dpf/gate/settings.py
ansys/dpf/gate/string_field_grpcapi.py
ansys/dpf/gate/support_grpcapi.py
ansys/dpf/gate/time_freq_support_grpcapi.py
ansys/dpf/gate/tmp_dir_grpcapi.py
ansys/dpf/gate/utils.py
ansys/dpf/gate/workflow_grpcapi.py
ansys/dpf/gate/generated/any_abstract_api.py
ansys/dpf/gate/generated/any_capi.py
ansys/dpf/gate/generated/capi.py
ansys/dpf/gate/generated/client_abstract_api.py
ansys/dpf/gate/generated/client_capi.py
ansys/dpf/gate/generated/collection_abstract_api.py
ansys/dpf/gate/generated/collection_capi.py
ansys/dpf/gate/generated/custom_type_field_abstract_api.py
ansys/dpf/gate/generated/custom_type_field_capi.py
ansys/dpf/gate/generated/cyclic_support_abstract_api.py
ansys/dpf/gate/generated/cyclic_support_capi.py
ansys/dpf/gate/generated/data_base_abstract_api.py
ansys/dpf/gate/generated/data_base_capi.py
ansys_dpf_gate-0.4.1.dist-info/LICENSE
ansys_dpf_gate-0.4.1.dist-info/METADATA
ansys_dpf_gate-0.4.1.dist-info/WHEEL
ansys_dpf_gate-0.4.1.dist-info/top_level.txt
ansys_dpf_gate-0.4.1.dist-info/RECORD
